libd/__init__.py
libd-0.1.0.dist-info/WHEEL
libd-0.1.0.dist-info/METADATA
libd-0.1.0.dist-info/RECORD
