Metadata-Version: 2.1
Name: libd
Version: 0.1.0
Summary: This is a library that contains all the advanced data structures that are otherwise not supported by Python native library.
Author: Tinu Tomson
Author-email: tinutomson@yahoo.com
Requires-Python: >=3.6,<4.0
Classifier: Programming Language :: Python :: 3
Classifier: Programming Language :: Python :: 3.6
Classifier: Programming Language :: Python :: 3.7
Classifier: Programming Language :: Python :: 3.8
Classifier: Programming Language :: Python :: 3.9
